nneve/__init__.py
nneve/__main__.py
nneve/cli/__init__.py
nneve/common/__init__.py
nneve/common/logconfig.py
nneve/common/model.py
nneve/navier_stokes/__init__.py
nneve/quantum_oscillator/__init__.py
nneve/quantum_oscillator/constants.py
nneve/quantum_oscillator/network.py
nneve/quantum_oscillator/params.py
nneve/quantum_oscillator/tracker.py
nneve/quantum_oscillator/examples/__init__.py
nneve/quantum_oscillator/examples/_qonetwork.py
nneve/quantum_oscillator/examples/_weights/s1.w
nneve/quantum_oscillator/examples/_weights/s2.w
nneve/quantum_oscillator/examples/_weights/s3.w
nneve/quantum_oscillator/examples/_weights/s4.w
nneve/quantum_oscillator/examples/_weights/s5.w
nneve/quantum_oscillator/examples/_weights/s6.w
nneve/quantum_oscillator/examples/_weights/s7.w
nneve/quantum_oscillator/layers/__init__.py
nneve/quantum_oscillator/layers/eigenvalue.py
nneve/utility/__init__.py
nneve/utility/plotting.py
nneve/utility/sysinfo.py
nneve/utility/testing.py
nneve-22.8.20.dist-info/AUTHORS
nneve-22.8.20.dist-info/LICENSE
nneve-22.8.20.dist-info/METADATA
nneve-22.8.20.dist-info/WHEEL
nneve-22.8.20.dist-info/entry_points.txt
nneve-22.8.20.dist-info/top_level.txt
nneve-22.8.20.dist-info/RECORD
