Metadata-Version: 2.1
Name: nneve
Version: 22.8.20
Summary: Neural Network Eigenvalue Estimator for quantum oscillator problem.
Home-page: https://github.com/Argmaster/nneve
Author: NNEVE team
Author-email: argmaster.world@gmail.com
License: LGPL-3.0
Project-URL: GitHub, https://github.com/Argmaster/nneve
Keywords: python-3,python-3.7,python-3.8,python-3.9,python-3.10
Platform: UNKNOWN
Classifier: Development Status :: 4 - Beta
Classifier: Intended Audience :: Developers
Classifier: Operating System :: Unix
Classifier: Operating System :: POSIX
Classifier: Operating System :: Microsoft :: Windows
Classifier: Programming Language :: Python :: 3
Classifier: Programming Language :: Python :: 3 :: Only
Classifier: Programming Language :: Python :: 3.7
Classifier: Programming Language :: Python :: 3.8
Classifier: Programming Language :: Python :: 3.9
Classifier: Programming Language :: Python :: 3.10
Classifier: Programming Language :: Python :: Implementation :: CPython
Classifier: Topic :: Utilities
Requires-Python: >=3.7
License-File: LICENSE
License-File: AUTHORS
Requires-Dist: click (<8.2.0,>=8.1.0)
Requires-Dist: matplotlib (<3.6.0,>=3.5.0)
Requires-Dist: numpy (<1.22.0,>=1.21.0)
Requires-Dist: packaging (<21.4.0,>=21.3.0)
Requires-Dist: pandas (<1.4.0,>=1.3.0)
Requires-Dist: rich (<12.1.0,>=12.0.0)
Requires-Dist: scipy (<1.8.0,>=1.7.0)
Requires-Dist: tensorflow (<2.9.0,>=2.8.0)
Requires-Dist: pillow (<9.2.0,>=9.1.0)
Requires-Dist: psutil (<5.10.0,>=5.9.0)
Requires-Dist: py-cpuinfo (<8.1.0,>=8.0.0)
Requires-Dist: pydantic (<1.10.0,>=1.9.0)
Requires-Dist: backports.cached-property (>=1.0.2)
Provides-Extra: dev
Requires-Dist: click (<8.2.0,>=8.1.0) ; extra == 'dev'
Requires-Dist: matplotlib (<3.6.0,>=3.5.0) ; extra == 'dev'
Requires-Dist: numpy (<1.22.0,>=1.21.0) ; extra == 'dev'
Requires-Dist: packaging (<21.4.0,>=21.3.0) ; extra == 'dev'
Requires-Dist: pandas (<1.4.0,>=1.3.0) ; extra == 'dev'
Requires-Dist: rich (<12.1.0,>=12.0.0) ; extra == 'dev'
Requires-Dist: scipy (<1.8.0,>=1.7.0) ; extra == 'dev'
Requires-Dist: tensorflow (<2.9.0,>=2.8.0) ; extra == 'dev'
Requires-Dist: pillow (<9.2.0,>=9.1.0) ; extra == 'dev'
Requires-Dist: psutil (<5.10.0,>=5.9.0) ; extra == 'dev'
Requires-Dist: py-cpuinfo (<8.1.0,>=8.0.0) ; extra == 'dev'
Requires-Dist: pydantic (<1.10.0,>=1.9.0) ; extra == 'dev'
Requires-Dist: backports.cached-property (>=1.0.2) ; extra == 'dev'
Requires-Dist: black (==22.3.0) ; extra == 'dev'
Requires-Dist: isort (==5.10.1) ; extra == 'dev'
Requires-Dist: docformatter (==1.4) ; extra == 'dev'
Requires-Dist: flake8 (==4.0.1) ; extra == 'dev'
Requires-Dist: flake8-alfred (==1.1.1) ; extra == 'dev'
Requires-Dist: flake8-broken-line (==0.4.0) ; extra == 'dev'
Requires-Dist: flake8-bugbear (==22.4.25) ; extra == 'dev'
Requires-Dist: flake8-builtins (==1.5.3) ; extra == 'dev'
Requires-Dist: flake8-cognitive-complexity (==0.1.0) ; extra == 'dev'
Requires-Dist: flake8-comprehensions (==3.8.0) ; extra == 'dev'
Requires-Dist: flake8-eradicate (==1.2.1) ; extra == 'dev'
Requires-Dist: flake8-expression-complexity (==0.0.11) ; extra == 'dev'
Requires-Dist: flake8-functions (==0.0.7) ; extra == 'dev'
Requires-Dist: flake8-functions-names (==0.1.0) ; extra == 'dev'
Requires-Dist: flake8-printf-formatting (==1.1.2) ; extra == 'dev'
Requires-Dist: flake8-pytest-style (==1.6.0) ; extra == 'dev'
Requires-Dist: flake8-simplify (==0.19.2) ; extra == 'dev'
Requires-Dist: pep8-naming (==0.12.1) ; extra == 'dev'
Requires-Dist: pre-commit (==2.18.1) ; extra == 'dev'
Requires-Dist: mkdocstrings ; extra == 'dev'
Requires-Dist: mkdocstrings[python] ; extra == 'dev'
Requires-Dist: jinja2 (==3.0.3) ; extra == 'dev'
Requires-Dist: mkdocs-macros-plugin (==0.7) ; extra == 'dev'
Requires-Dist: mdx-truly-sane-lists (==1.2) ; extra == 'dev'
Requires-Dist: setuptools (==62.1.0) ; extra == 'dev'
Requires-Dist: wheel (==0.37.1) ; extra == 'dev'
Requires-Dist: tox (==3.24.5) ; extra == 'dev'
Requires-Dist: click (==8.1) ; extra == 'dev'
Requires-Dist: pytest (==7.1.2) ; extra == 'dev'
Requires-Dist: pytest-cov (==3.0.0) ; extra == 'dev'
Requires-Dist: hypothesis (<6.47.0,>=6.46.0) ; extra == 'dev'
Requires-Dist: mypy (==0.950) ; extra == 'dev'
Requires-Dist: lxml (==4.8.0) ; extra == 'dev'
Requires-Dist: mkdocs (<1.3.0,>=1.2.0) ; (python_version <= "3.8") and extra == 'dev'
Requires-Dist: mkdocs-material (==8.2.5) ; (python_version <= "3.8") and extra == 'dev'
Requires-Dist: mkdocs (<1.4.0,>=1.3.0) ; (python_version > "3.8") and extra == 'dev'
Requires-Dist: mkdocs-material (==8.2.13) ; (python_version > "3.8") and extra == 'dev'
